[
    {
        "index": 1,
        "name": "Goribi-Bank",
        "codeBase": "GitHub",
        "urlLive": "goribi-bank/index.html",
        "urlCode": "https://github.com/EkramH/my-js/tree/main/goribi-bank",
        "bgColor": "bg-white"

    },
    {
        "index": 2,
        "name": "To-Do List",
        "codeBase": "GitHub",
        "urlLive": "to-do-list/index.html",
        "urlCode": "https://github.com/EkramH/my-js/tree/main/to-do-list",
        "bgColor": "bg-gray-100"
    },
    {
        "index": 3,
        "name": "Weather-App",
        "codeBase": "GitHub",
        "urlLive": "weather app/index.html",
        "urlCode": "https://github.com/EkramH/my-js/tree/main/weather%20app",
        "bgColor": "bg-white"
    },
    {
        "index": 4,
        "name": "Drum-Kit",
        "codeBase": "GitHub",
        "urlLive": "drum-kit/index.html",
        "urlCode": "https://github.com/EkramH/my-js/tree/main/drum-kit",
        "bgColor": "bg-gray-100"
    }
]